CHANGES.txt
LICENSE.txt
MANIFEST.in
README.org
setup.py
sshmount_netrc
bin/sshmount-netrc
sshmount_netrc/__init__.py
sshmount_netrc/sshmount_netrc.py
sshmount_netrc.egg-info/PKG-INFO
sshmount_netrc.egg-info/SOURCES.txt
sshmount_netrc.egg-info/dependency_links.txt
sshmount_netrc.egg-info/top_level.txt