Metadata-Version: 1.0
Name: sshmount-netrc
Version: 0.1.15
Summary: ssh mount using passwords saved in .netrc
Home-page: https://github.com/tjaartvdwalt/sshmount-netrc
Author: Tjaart van der Walt
Author-email: pypi@tjaart.co.za
License: MIT
Platform: Linux
